ppipe/__init__.py
ppipe/__main__.py
ppipe/acl_changer.py
ppipe/aoi.json
ppipe/assetsizes.py
ppipe/async_download.py
ppipe/cli_aoi2json.py
ppipe/cli_metadata.py
ppipe/config.py
ppipe/ee_ls.py
ppipe/kml_aoi.py
ppipe/logconfig.json
ppipe/manifest_lib.py
ppipe/metadata_ingest.py
ppipe/metadata_loader.py
ppipe/planet_quota.py
ppipe/ppipe.py
ppipe/saved_search_download.py
ppipe/sel-latest-linux.py
ppipe/sel-latest-mac.py
ppipe/sel-latest-win.py
ppipe/sel_setup.py
ppipe/sr_metadata.py
ppipe/wrs_grid.csv
ppipe-0.4.9.dist-info/METADATA
ppipe-0.4.9.dist-info/RECORD
ppipe-0.4.9.dist-info/WHEEL
ppipe-0.4.9.dist-info/entry_points.txt
ppipe-0.4.9.dist-info/top_level.txt
