Metadata-Version: 2.1
Name: ppipe
Version: 0.4.9
Summary: Planet API Pipeline & Google Earth Engine Batch Assets Manager with Addons
Home-page: https://github.com/samapriya/Planet-GEE-Pipeline-CLI
Author: Samapriya Roy
Author-email: samapriya.roy@gmail.com
License: Apache 2.0
Platform: UNKNOWN
Classifier: Development Status :: 3 - Alpha
Classifier: Intended Audience :: Developers
Classifier: Intended Audience :: Science/Research
Classifier: Natural Language :: English
Classifier: License :: OSI Approved :: Apache Software License
Classifier: Programming Language :: Python
Classifier: Programming Language :: Python :: 2.7
Classifier: Programming Language :: Python :: 3.6
Classifier: Operating System :: OS Independent
Classifier: Topic :: Scientific/Engineering :: GIS
Requires-Dist: bs4 (>=0.0.1)
Requires-Dist: clipboard (>=0.0.4)
Requires-Dist: earthengine-api (>=0.1.138)
Requires-Dist: future (>=0.16.0)
Requires-Dist: google-cloud-storage (>=1.5.0)
Requires-Dist: planet (>=1.1.0)
Requires-Dist: pandas (>=0.23.0)
Requires-Dist: psutil (>=5.4.5)
Requires-Dist: pyOpenSSL (>=19.0.0)
Requires-Dist: pyshp (>=1.2.12)
Requires-Dist: pytest (>=3.5.1)
Requires-Dist: requests-toolbelt (>=0.8.0)
Requires-Dist: retrying (>=1.3.3)
Requires-Dist: simplejson (>=3.15.0)
Requires-Dist: selenium (>=3.13.0)
Requires-Dist: pathlib (>=1.0.1)
Requires-Dist: lxml (>=4.1.1)
Requires-Dist: beautifulsoup4 (>=4.5.1)
Requires-Dist: pypiwin32; platform_system == "Windows"
Requires-Dist: pywin32; platform_system == "Windows"
Requires-Dist: pySmartDL (==1.2.5); python_version < "3.4"
Requires-Dist: pySmartDL (>=1.3.1); python_version > "3.4"
